{"timezones": [{"value": "Dateline Standard Time", "abbr": "DST", "offset": -12, "isdst": false, "text": "(UTC-12:00) International Date Line West", "utc": ["Etc/GMT+12"]}, {"value": "UTC-11", "abbr": "U", "offset": -11, "isdst": false, "text": "(UTC-11:00) Coordinated Universal Time-11", "utc": ["Etc/GMT+11", "Pacific/Midway", "Pacific/Niue", "Pacific/Pago_Pago"]}, {"value": "Hawaiian Standard Time", "abbr": "HST", "offset": -10, "isdst": false, "text": "(UTC-10:00) Hawaii", "utc": ["Etc/GMT+10", "Pacific/Honolulu", "Pacific/Johnston", "Pacific/Rarotonga", "Pacific/Tahiti"]}, {"value": "Alaskan Standard Time", "abbr": "AKDT", "offset": -8, "isdst": true, "text": "(UTC-09:00) Alaska", "utc": ["America/Anchorage", "America/Juneau", "America/Nome", "America/Sitka", "America/Yakutat"]}, {"value": "Pacific Standard Time (Mexico)", "abbr": "PDT", "offset": -7, "isdst": true, "text": "(UTC-08:00) Baja California", "utc": ["America/Santa_Isabel"]}, {"value": "Pacific Daylight Time", "abbr": "PDT", "offset": -7, "isdst": true, "text": "(UTC-07:00) Pacific Time (US & Canada)", "utc": ["America/Dawson", "America/Los_Angeles", "America/Tijuana", "America/Vancouver", "America/Whitehorse"]}, {"value": "Pacific Standard Time", "abbr": "PST", "offset": -8, "isdst": false, "text": "(UTC-08:00) Pacific Time (US & Canada)", "utc": ["America/Dawson", "America/Los_Angeles", "America/Tijuana", "America/Vancouver", "America/Whitehorse", "PST8PDT"]}, {"value": "US Mountain Standard Time", "abbr": "UMST", "offset": -7, "isdst": false, "text": "(UTC-07:00) Arizona", "utc": ["America/Creston", "America/Dawson_Creek", "America/Hermosillo", "America/Phoenix", "Etc/GMT+7"]}, {"value": "Mountain Standard Time (Mexico)", "abbr": "MDT", "offset": -6, "isdst": true, "text": "(UTC-07:00) Chihuahua, La Paz, Mazatlan", "utc": ["America/Chihuahua", "America/Mazatlan"]}, {"value": "Mountain Standard Time", "abbr": "MDT", "offset": -6, "isdst": true, "text": "(UTC-07:00) Mountain Time (US & Canada)", "utc": ["America/Boise", "America/Cambridge_Bay", "America/Denver", "America/Edmonton", "America/Inuvik", "America/Ojinaga", "America/Yellowknife", "MST7MDT"]}, {"value": "Central America Standard Time", "abbr": "CAST", "offset": -6, "isdst": false, "text": "(UTC-06:00) Central America", "utc": ["America/Belize", "America/Costa_Rica", "America/El_Salvador", "America/Guatemala", "America/Managua", "America/Tegucigalpa", "Etc/GMT+6", "Pacific/Galapagos"]}, {"value": "Central Standard Time", "abbr": "CDT", "offset": -5, "isdst": true, "text": "(UTC-06:00) Central Time (US & Canada)", "utc": ["America/Chicago", "America/Indiana/Knox", "America/Indiana/Tell_City", "America/Matamoros", "America/Menominee", "America/North_Dakota/Beulah", "America/North_Dakota/Center", "America/North_Dakota/New_Salem", "America/Rainy_River", "America/Rankin_Inlet", "America/Resolute", "America/Winnipeg", "CST6CDT"]}, {"value": "Central Standard Time (Mexico)", "abbr": "CDT", "offset": -5, "isdst": true, "text": "(UTC-06:00) Guadalajara, Mexico City, Monterrey", "utc": ["America/Bahia_Banderas", "America/Cancun", "America/Merida", "America/Mexico_City", "America/Monterrey"]}, {"value": "Canada Central Standard Time", "abbr": "CCST", "offset": -6, "isdst": false, "text": "(UTC-06:00) Saskatchewan", "utc": ["America/Regina", "America/Swift_Current"]}, {"value": "SA Pacific Standard Time", "abbr": "SPST", "offset": -5, "isdst": false, "text": "(UTC-05:00) Bogota, Lima, Quito", "utc": ["America/Bogota", "America/Cayman", "America/Coral_Harbour", "America/Eirunepe", "America/Guayaquil", "America/Jamaica", "America/Lima", "America/Panama", "America/Rio_Branco", "Etc/GMT+5"]}, {"value": "Eastern Standard Time", "abbr": "EDT", "offset": -4, "isdst": true, "text": "(UTC-05:00) Eastern Time (US & Canada)", "utc": ["America/Detroit", "America/Havana", "America/Indiana/Petersburg", "America/Indiana/Vincennes", "America/Indiana/Winamac", "America/Iqaluit", "America/Kentucky/Monticello", "America/Louisville", "America/Montreal", "America/Nassau", "America/New_York", "America/Nipigon", "America/Pangnirtung", "America/Port-au-Prince", "America/Thunder_Bay", "America/Toronto", "EST5EDT"]}, {"value": "US Eastern Standard Time", "abbr": "UEDT", "offset": -4, "isdst": true, "text": "(UTC-05:00) Indiana (East)", "utc": ["America/Indiana/Marengo", "America/Indiana/Vevay", "America/Indianapolis"]}, {"value": "Venezuela Standard Time", "abbr": "VST", "offset": -4.5, "isdst": false, "text": "(UTC-04:30) Caracas", "utc": ["America/Caracas"]}, {"value": "Paraguay Standard Time", "abbr": "PYT", "offset": -4, "isdst": false, "text": "(UTC-04:00) Asuncion", "utc": ["America/Asuncion"]}, {"value": "Atlantic Standard Time", "abbr": "ADT", "offset": -3, "isdst": true, "text": "(UTC-04:00) Atlantic Time (Canada)", "utc": ["America/Glace_Bay", "America/Goose_Bay", "America/Halifax", "America/Moncton", "America/Thule", "Atlantic/Bermuda"]}, {"value": "Central Brazilian Standard Time", "abbr": "CBST", "offset": -4, "isdst": false, "text": "(UTC-04:00) Cuiaba", "utc": ["America/Campo_Grande", "America/Cuiaba"]}, {"value": "SA Western Standard Time", "abbr": "SWST", "offset": -4, "isdst": false, "text": "(UTC-04:00) Georgetown, La Paz, Manaus, San Juan", "utc": ["America/Anguilla", "America/Antigua", "America/Aruba", "America/Barbados", "America/Blanc-Sablon", "America/Boa_Vista", "America/Curacao", "America/Dominica", "America/Grand_Turk", "America/Grenada", "America/Guadeloupe", "America/Guyana", "America/Kralendijk", "America/La_Paz", "America/Lower_Princes", "America/Manaus", "America/Marigot", "America/Martinique", "America/Montserrat", "America/Port_of_Spain", "America/Porto_Velho", "America/Puerto_Rico", "America/Santo_Domingo", "America/St_Barthelemy", "America/St_Kitts", "America/St_Lucia", "America/St_Thomas", "America/St_Vincent", "America/Tortola", "Etc/GMT+4"]}, {"value": "Pacific SA Standard Time", "abbr": "PSST", "offset": -4, "isdst": false, "text": "(UTC-04:00) Santiago", "utc": ["America/Santiago", "Antarctica/Palmer"]}, {"value": "Newfoundland Standard Time", "abbr": "NDT", "offset": -2.5, "isdst": true, "text": "(UTC-03:30) Newfoundland", "utc": ["America/St_Johns"]}, {"value": "E. South America Standard Time", "abbr": "ESAST", "offset": -3, "isdst": false, "text": "(UTC-03:00) Brasilia", "utc": ["America/Sao_Paulo"]}, {"value": "Argentina Standard Time", "abbr": "AST", "offset": -3, "isdst": false, "text": "(UTC-03:00) Buenos Aires", "utc": ["America/Argentina/La_Rioja", "America/Argentina/Rio_Gallegos", "America/Argentina/Salta", "America/Argentina/San_Juan", "America/Argentina/San_Luis", "America/Argentina/Tucuman", "America/Argentina/Ushuaia", "America/Buenos_Aires", "America/Catamarca", "America/Cordoba", "America/Jujuy", "America/Mendoza"]}, {"value": "SA Eastern Standard Time", "abbr": "SEST", "offset": -3, "isdst": false, "text": "(UTC-03:00) Cayenne, Fortaleza", "utc": ["America/Araguaina", "America/Belem", "America/Cayenne", "America/Fortaleza", "America/Maceio", "America/Paramaribo", "America/Recife", "America/Santarem", "Antarctica/Rothera", "Atlantic/Stanley", "Etc/GMT+3"]}, {"value": "Greenland Standard Time", "abbr": "GDT", "offset": -3, "isdst": true, "text": "(UTC-03:00) Greenland", "utc": ["America/Godthab"]}, {"value": "Montevideo Standard Time", "abbr": "MST", "offset": -3, "isdst": false, "text": "(UTC-03:00) Montevideo", "utc": ["America/Montevideo"]}, {"value": "Bahia Standard Time", "abbr": "BST", "offset": -3, "isdst": false, "text": "(UTC-03:00) Salvador", "utc": ["America/Bahia"]}, {"value": "UTC-02", "abbr": "U", "offset": -2, "isdst": false, "text": "(UTC-02:00) Coordinated Universal Time-02", "utc": ["America/Noronha", "Atlantic/South_Georgia", "Etc/GMT+2"]}, {"value": "Mid-Atlantic Standard Time", "abbr": "MDT", "offset": -1, "isdst": true, "text": "(UTC-02:00) Mid-Atlantic - Old", "utc": []}, {"value": "Azores Standard Time", "abbr": "ADT", "offset": 0, "isdst": true, "text": "(UTC-01:00) Azores", "utc": ["America/Scoresbysund", "Atlantic/Azores"]}, {"value": "Cape Verde Standard Time", "abbr": "CVST", "offset": -1, "isdst": false, "text": "(UTC-01:00) Cape Verde Is.", "utc": ["Atlantic/Cape_Verde", "Etc/GMT+1"]}, {"value": "Morocco Standard Time", "abbr": "MDT", "offset": 1, "isdst": true, "text": "(UTC) Casablanca", "utc": ["Africa/Casablanca", "Africa/El_Aaiun"]}, {"value": "UTC", "abbr": "UTC", "offset": 0, "isdst": false, "text": "(UTC) Coordinated Universal Time", "utc": ["America/Danmarkshavn", "Etc/GMT"]}, {"value": "GMT Standard Time", "abbr": "GMT", "offset": 0, "isdst": false, "text": "(UTC) Edinburgh, London", "utc": ["Europe/Isle_of_Man", "Europe/Guernsey", "Europe/Jersey", "Europe/London"]}, {"value": "British Summer Time", "abbr": "BST", "offset": 1, "isdst": true, "text": "(UTC+01:00) Edinburgh, London", "utc": ["Europe/Isle_of_Man", "Europe/Guernsey", "Europe/Jersey", "Europe/London"]}, {"value": "GMT Standard Time", "abbr": "GDT", "offset": 1, "isdst": true, "text": "(UTC) Dublin, Lisbon", "utc": ["Atlantic/Canary", "Atlantic/Faeroe", "Atlantic/Madeira", "Europe/Dublin", "Europe/Lisbon"]}, {"value": "Greenwich Standard Time", "abbr": "GST", "offset": 0, "isdst": false, "text": "(UTC) Monrovia, Reykjavik", "utc": ["Africa/Abidjan", "Africa/Accra", "Africa/Bamako", "Africa/Banjul", "Africa/Bissau", "Africa/Conakry", "Africa/Dakar", "Africa/Freetown", "Africa/Lome", "Africa/Monrovia", "Africa/Nouakchott", "Africa/Ouagadougou", "Africa/Sao_Tome", "Atlantic/Reykjavik", "Atlantic/St_Helena"]}, {"value": "W. Europe Standard Time", "abbr": "WEDT", "offset": 2, "isdst": true, "text": "(UTC+01:00) Amsterdam, Berlin, Bern, Rome, Stockholm, Vienna", "utc": ["Arctic/Longyearbyen", "Europe/Amsterdam", "Europe/Andorra", "Europe/Berlin", "Europe/Busingen", "Europe/Gibraltar", "Europe/Luxembourg", "Europe/Malta", "Europe/Monaco", "Europe/Oslo", "Europe/Rome", "Europe/San_Marino", "Europe/Stockholm", "Europe/Vaduz", "Europe/Vatican", "Europe/Vienna", "Europe/Zurich"]}, {"value": "Central Europe Standard Time", "abbr": "CEDT", "offset": 2, "isdst": true, "text": "(UTC+01:00) Belgrade, Bratislava, Budapest, Ljubljana, Prague", "utc": ["Europe/Belgrade", "Europe/Bratislava", "Europe/Budapest", "Europe/Ljubljana", "Europe/Podgorica", "Europe/Prague", "Europe/Tirane"]}, {"value": "Romance Standard Time", "abbr": "RDT", "offset": 2, "isdst": true, "text": "(UTC+01:00) Brussels, Copenhagen, Madrid, Paris", "utc": ["Africa/Ceuta", "Europe/Brussels", "Europe/Copenhagen", "Europe/Madrid", "Europe/Paris"]}, {"value": "Central European Standard Time", "abbr": "CEDT", "offset": 2, "isdst": true, "text": "(UTC+01:00) Sarajevo, Skopje, Warsaw, Zagreb", "utc": ["Europe/Sarajevo", "Europe/Skopje", "Europe/Warsaw", "Europe/Zagreb"]}, {"value": "W. Central Africa Standard Time", "abbr": "WCAST", "offset": 1, "isdst": false, "text": "(UTC+01:00) West Central Africa", "utc": ["Africa/Algiers", "Africa/Bangui", "Africa/Brazzaville", "Africa/Douala", "Africa/Kinshasa", "Africa/Lagos", "Africa/Libreville", "Africa/Luanda", "Africa/Malabo", "Africa/Ndjamena", "Africa/Niamey", "Africa/Porto-Novo", "Africa/Tunis", "Etc/GMT-1"]}, {"value": "Namibia Standard Time", "abbr": "NST", "offset": 1, "isdst": false, "text": "(UTC+01:00) Windhoek", "utc": ["Africa/Windhoek"]}, {"value": "GTB Standard Time", "abbr": "GDT", "offset": 3, "isdst": true, "text": "(UTC+02:00) Athens, Bucharest", "utc": ["Asia/Nicosia", "Europe/Athens", "Europe/Bucharest", "Europe/Chisinau"]}, {"value": "Middle East Standard Time", "abbr": "MEDT", "offset": 3, "isdst": true, "text": "(UTC+02:00) Beirut", "utc": ["Asia/Beirut"]}, {"value": "Egypt Standard Time", "abbr": "EST", "offset": 2, "isdst": false, "text": "(UTC+02:00) Cairo", "utc": ["Africa/Cairo"]}, {"value": "Syria Standard Time", "abbr": "SDT", "offset": 3, "isdst": true, "text": "(UTC+02:00) Damascus", "utc": ["Asia/Damascus"]}, {"value": "E. Europe Standard Time", "abbr": "EEDT", "offset": 3, "isdst": true, "text": "(UTC+02:00) E. Europe", "utc": ["Asia/Nicosia", "Europe/Athens", "Europe/Bucharest", "Europe/Chisinau", "Europe/Helsinki", "Europe/Kiev", "Europe/Mariehamn", "Europe/Nicosia", "Europe/Riga", "Europe/Sofia", "Europe/Tallinn", "Europe/Uzhgorod", "Europe/Vilnius", "Europe/Zaporozhye"]}, {"value": "South Africa Standard Time", "abbr": "SAST", "offset": 2, "isdst": false, "text": "(UTC+02:00) Harare, Pretoria", "utc": ["Africa/Blantyre", "Africa/Bujumbura", "Africa/Gaborone", "Africa/Harare", "Africa/Johannesburg", "Africa/Kigali", "Africa/Lubumbashi", "Africa/Lusaka", "Africa/Maputo", "Africa/Maseru", "Africa/Mbabane", "Etc/GMT-2"]}, {"value": "FLE Standard Time", "abbr": "FDT", "offset": 3, "isdst": true, "text": "(UTC+02:00) Helsinki, Kyiv, Riga, Sofia, Tallinn, Vilnius", "utc": ["Europe/Helsinki", "Europe/Kiev", "Europe/Mariehamn", "Europe/Riga", "Europe/Sofia", "Europe/Tallinn", "Europe/Uzhgorod", "Europe/Vilnius", "Europe/Zaporozhye"]}, {"value": "Turkey Standard Time", "abbr": "TDT", "offset": 3, "isdst": false, "text": "(UTC+03:00) Istanbul", "utc": ["Europe/Istanbul"]}, {"value": "Israel Standard Time", "abbr": "JDT", "offset": 3, "isdst": true, "text": "(UTC+02:00) Jerusalem", "utc": ["Asia/Jerusalem"]}, {"value": "Libya Standard Time", "abbr": "LST", "offset": 2, "isdst": false, "text": "(UTC+02:00) Tripoli", "utc": ["Africa/Tripoli"]}, {"value": "Jordan Standard Time", "abbr": "JST", "offset": 3, "isdst": false, "text": "(UTC+03:00) Amman", "utc": ["Asia/Amman"]}, {"value": "Arabic Standard Time", "abbr": "AST", "offset": 3, "isdst": false, "text": "(UTC+03:00) Baghdad", "utc": ["Asia/Baghdad"]}, {"value": "Kaliningrad Standard Time", "abbr": "KST", "offset": 3, "isdst": false, "text": "(UTC+02:00) Kaliningrad", "utc": ["Europe/Kaliningrad"]}, {"value": "Arab Standard Time", "abbr": "AST", "offset": 3, "isdst": false, "text": "(UTC+03:00) Kuwait, Riyadh", "utc": ["Asia/Aden", "Asia/Bahrain", "Asia/Kuwait", "Asia/Qatar", "Asia/Riyadh"]}, {"value": "E. Africa Standard Time", "abbr": "EAST", "offset": 3, "isdst": false, "text": "(UTC+03:00) Nairobi", "utc": ["Africa/Addis_Ababa", "Africa/Asmera", "Africa/Dar_es_Salaam", "Africa/Djibouti", "Africa/Juba", "Africa/Kampala", "Africa/Khartoum", "Africa/Mogadishu", "Africa/Nairobi", "Antarctica/Syowa", "Etc/GMT-3", "Indian/Antananarivo", "Indian/Comoro", "Indian/Mayotte"]}, {"value": "Moscow Standard Time", "abbr": "MSK", "offset": 3, "isdst": false, "text": "(UTC+03:00) Moscow, St. Petersburg, Volgograd, Minsk", "utc": ["Europe/Kirov", "Europe/Moscow", "Europe/Simferopol", "Europe/Volgograd", "Europe/Minsk"]}, {"value": "Samara Time", "abbr": "SAMT", "offset": 4, "isdst": false, "text": "(UTC+04:00) Samara, Ulyanovsk, Saratov", "utc": ["Europe/Astrakhan", "Europe/Samara", "Europe/Ulyanovsk"]}, {"value": "Iran Standard Time", "abbr": "IDT", "offset": 4.5, "isdst": true, "text": "(UTC+03:30) Tehran", "utc": ["Asia/Tehran"]}, {"value": "Arabian Standard Time", "abbr": "AST", "offset": 4, "isdst": false, "text": "(UTC+04:00) Abu Dhabi, Muscat", "utc": ["Asia/Dubai", "Asia/Muscat", "Etc/GMT-4"]}, {"value": "Azerbaijan Standard Time", "abbr": "ADT", "offset": 5, "isdst": true, "text": "(UTC+04:00) Baku", "utc": ["Asia/Baku"]}, {"value": "Mauritius Standard Time", "abbr": "MST", "offset": 4, "isdst": false, "text": "(UTC+04:00) Port Louis", "utc": ["Indian/Mahe", "Indian/Mauritius", "Indian/Reunion"]}, {"value": "Georgian Standard Time", "abbr": "GET", "offset": 4, "isdst": false, "text": "(UTC+04:00) Tbilisi", "utc": ["Asia/Tbilisi"]}, {"value": "Caucasus Standard Time", "abbr": "CST", "offset": 4, "isdst": false, "text": "(UTC+04:00) Yerevan", "utc": ["Asia/Yerevan"]}, {"value": "Afghanistan Standard Time", "abbr": "AST", "offset": 4.5, "isdst": false, "text": "(UTC+04:30) Kabul", "utc": ["Asia/Kabul"]}, {"value": "West Asia Standard Time", "abbr": "WAST", "offset": 5, "isdst": false, "text": "(UTC+05:00) Ashgabat, Tashkent", "utc": ["Antarctica/Mawson", "Asia/Aqtau", "Asia/Aqtobe", "Asia/Ashgabat", "Asia/Dushanbe", "Asia/Oral", "Asia/Samarkand", "Asia/Tashkent", "Etc/GMT-5", "Indian/Kerguelen", "Indian/Maldives"]}, {"value": "Yekaterinburg Time", "abbr": "YEKT", "offset": 5, "isdst": false, "text": "(UTC+05:00) Yekaterinburg", "utc": ["Asia/Yekaterinburg"]}, {"value": "Pakistan Standard Time", "abbr": "PKT", "offset": 5, "isdst": false, "text": "(UTC+05:00) Islamabad, Karachi", "utc": ["Asia/Karachi"]}, {"value": "India Standard Time", "abbr": "IST", "offset": 5.5, "isdst": false, "text": "(UTC+05:30) Chennai, Kolkata, Mumbai, New Delhi", "utc": ["Asia/Kolkata"]}, {"value": "Sri Lanka Standard Time", "abbr": "SLST", "offset": 5.5, "isdst": false, "text": "(UTC+05:30) Sri Jayawardenepura", "utc": ["Asia/Colombo"]}, {"value": "Nepal Standard Time", "abbr": "NST", "offset": 5.75, "isdst": false, "text": "(UTC+05:45) Kathmandu", "utc": ["Asia/Kathmandu"]}, {"value": "Central Asia Standard Time", "abbr": "CAST", "offset": 6, "isdst": false, "text": "(UTC+06:00) Nur-Sultan (Astana)", "utc": ["Antarctica/Vostok", "Asia/Almaty", "Asia/Bishkek", "Asia/Qyzylorda", "Asia/Urumqi", "Etc/GMT-6", "Indian/Chagos"]}, {"value": "Bangladesh Standard Time", "abbr": "BST", "offset": 6, "isdst": false, "text": "(UTC+06:00) Dhaka", "utc": ["Asia/Dhaka", "Asia/Thimphu"]}, {"value": "Myanmar Standard Time", "abbr": "MST", "offset": 6.5, "isdst": false, "text": "(UTC+06:30) Yangon (Rangoon)", "utc": ["Asia/Rangoon", "Indian/Cocos"]}, {"value": "SE Asia Standard Time", "abbr": "SAST", "offset": 7, "isdst": false, "text": "(UTC+07:00) Bangkok, Hanoi, Jakarta", "utc": ["Antarctica/Davis", "Asia/Bangkok", "Asia/Hovd", "Asia/Jakarta", "Asia/Phnom_Penh", "Asia/Pontianak", "Asia/Saigon", "Asia/Vientiane", "Etc/GMT-7", "Indian/Christmas"]}, {"value": "N. Central Asia Standard Time", "abbr": "NCAST", "offset": 7, "isdst": false, "text": "(UTC+07:00) Novosibirsk", "utc": ["Asia/Novokuznetsk", "Asia/Novosibirsk", "Asia/Omsk"]}, {"value": "China Standard Time", "abbr": "CST", "offset": 8, "isdst": false, "text": "(UTC+08:00) Beijing, Chongqing, Hong Kong, Urumqi", "utc": ["Asia/Hong_Kong", "Asia/Macau", "Asia/Shanghai"]}, {"value": "North Asia Standard Time", "abbr": "NAST", "offset": 8, "isdst": false, "text": "(UTC+08:00) Krasnoyarsk", "utc": ["Asia/Krasnoyarsk"]}, {"value": "Singapore Standard Time", "abbr": "MPST", "offset": 8, "isdst": false, "text": "(UTC+08:00) Kuala Lumpur, Singapore", "utc": ["Asia/Brunei", "Asia/Kuala_Lumpur", "Asia/Kuching", "Asia/Makassar", "Asia/Manila", "Asia/Singapore", "Etc/GMT-8"]}, {"value": "W. Australia Standard Time", "abbr": "WAST", "offset": 8, "isdst": false, "text": "(UTC+08:00) Perth", "utc": ["Antarctica/Casey", "Australia/Perth"]}, {"value": "Taipei Standard Time", "abbr": "TST", "offset": 8, "isdst": false, "text": "(UTC+08:00) Taipei", "utc": ["Asia/Taipei"]}, {"value": "Ulaanbaatar Standard Time", "abbr": "UST", "offset": 8, "isdst": false, "text": "(UTC+08:00) Ulaanbaatar", "utc": ["Asia/Choibalsan", "Asia/Ulaanbaatar"]}, {"value": "North Asia East Standard Time", "abbr": "NAEST", "offset": 8, "isdst": false, "text": "(UTC+08:00) Irkutsk", "utc": ["Asia/Irkutsk"]}, {"value": "Japan Standard Time", "abbr": "JST", "offset": 9, "isdst": false, "text": "(UTC+09:00) Osaka, Sapporo, Tokyo", "utc": ["Asia/Dili", "Asia/Jayapura", "Asia/Tokyo", "Etc/GMT-9", "Pacific/Palau"]}, {"value": "Korea Standard Time", "abbr": "KST", "offset": 9, "isdst": false, "text": "(UTC+09:00) Seoul", "utc": ["Asia/Pyongyang", "Asia/Seoul"]}, {"value": "Cen. Australia Standard Time", "abbr": "CAST", "offset": 9.5, "isdst": false, "text": "(UTC+09:30) Adelaide", "utc": ["Australia/Adelaide", "Australia/Broken_Hill"]}, {"value": "AUS Central Standard Time", "abbr": "ACST", "offset": 9.5, "isdst": false, "text": "(UTC+09:30) Darwin", "utc": ["Australia/Darwin"]}, {"value": "E. Australia Standard Time", "abbr": "EAST", "offset": 10, "isdst": false, "text": "(UTC+10:00) Brisbane", "utc": ["Australia/Brisbane", "Australia/Lindeman"]}, {"value": "AUS Eastern Standard Time", "abbr": "AEST", "offset": 10, "isdst": false, "text": "(UTC+10:00) Canberra, Melbourne, Sydney", "utc": ["Australia/Melbourne", "Australia/Sydney"]}, {"value": "West Pacific Standard Time", "abbr": "WPST", "offset": 10, "isdst": false, "text": "(UTC+10:00) Guam, Port Moresby", "utc": ["Antarctica/DumontDUrville", "Etc/GMT-10", "Pacific/Guam", "Pacific/Port_Moresby", "Pacific/Saipan", "Pacific/Truk"]}, {"value": "Tasmania Standard Time", "abbr": "TST", "offset": 10, "isdst": false, "text": "(UTC+10:00) Hobart", "utc": ["Australia/Currie", "Australia/Hobart"]}, {"value": "Yakutsk Standard Time", "abbr": "YST", "offset": 9, "isdst": false, "text": "(UTC+09:00) Yakutsk", "utc": ["Asia/Chita", "Asia/Khandyga", "Asia/Yakutsk"]}, {"value": "Central Pacific Standard Time", "abbr": "CPST", "offset": 11, "isdst": false, "text": "(UTC+11:00) Solomon Is., New Caledonia", "utc": ["Antarctica/Macquarie", "Etc/GMT-11", "Pacific/Efate", "Pacific/Guadalcanal", "Pacific/Kosrae", "Pacific/Noumea", "Pacific/Ponape"]}, {"value": "Vladivostok Standard Time", "abbr": "VST", "offset": 11, "isdst": false, "text": "(UTC+11:00) Vladivostok", "utc": ["Asia/Sakhalin", "Asia/Ust-Nera", "Asia/Vladivostok"]}, {"value": "New Zealand Standard Time", "abbr": "NZST", "offset": 12, "isdst": false, "text": "(UTC+12:00) Auckland, Wellington", "utc": ["Antarctica/McMurdo", "Pacific/Auckland"]}, {"value": "UTC+12", "abbr": "U", "offset": 12, "isdst": false, "text": "(UTC+12:00) Coordinated Universal Time+12", "utc": ["Etc/GMT-12", "Pacific/Funafuti", "Pacific/Kwajalein", "Pacific/Majuro", "Pacific/Nauru", "Pacific/Tarawa", "Pacific/Wake", "Pacific/Wallis"]}, {"value": "Fiji Standard Time", "abbr": "FST", "offset": 12, "isdst": false, "text": "(UTC+12:00) Fiji", "utc": ["Pacific/Fiji"]}, {"value": "Magadan Standard Time", "abbr": "MST", "offset": 12, "isdst": false, "text": "(UTC+12:00) Magadan", "utc": ["Asia/Anadyr", "Asia/Kamchatka", "Asia/Magadan", "Asia/Srednekolymsk"]}, {"value": "Kamchatka Standard Time", "abbr": "KDT", "offset": 13, "isdst": true, "text": "(UTC+12:00) Petropavlovsk-Kamchatsky - Old", "utc": ["Asia/Kamchatka"]}, {"value": "Tonga Standard Time", "abbr": "TST", "offset": 13, "isdst": false, "text": "(UTC+13:00) Nuku'alofa", "utc": ["Etc/GMT-13", "Pacific/Enderbury", "Pacific/Fakaofo", "Pacific/Tongatapu"]}, {"value": "Samoa Standard Time", "abbr": "SST", "offset": 13, "isdst": false, "text": "(UTC+13:00) Samoa", "utc": ["Pacific/Apia"]}], "search_names": {"(UTC-12:00) International Date Line West": 0, "DST": 0, "Dateline Standard Time": 0, "Etc - GMT+12": 0, "GMT+12": 0, "(UTC-11:00) Coordinated Universal Time-11": 1, "U": 100, "UTC-11": 1, "Etc - GMT+11": 1, "GMT+11": 1, "Pacific - Midway": 1, "Midway": 1, "Pacific - Niue": 1, "Niue": 1, "Pacific - Pago_Pago": 1, "Pago_Pago": 1, "(UTC-10:00) Hawaii": 2, "HST": 2, "Hawaiian Standard Time": 2, "Etc - GMT+10": 2, "GMT+10": 2, "Pacific - Honolulu": 2, "Honolulu": 2, "Pacific - Johnston": 2, "Johnston": 2, "Pacific - Rarotonga": 2, "Rarotonga": 2, "Pacific - Tahiti": 2, "Tahiti": 2, "(UTC-09:00) Alaska": 3, "AKDT": 3, "Alaskan Standard Time": 3, "America - Anchorage": 3, "Anchorage": 3, "America - Juneau": 3, "Juneau": 3, "America - Nome": 3, "Nome": 3, "America - Sitka": 3, "Sitka": 3, "America - Yakutat": 3, "Yakutat": 3, "(UTC-08:00) Baja California": 4, "PDT": 5, "Pacific Standard Time (Mexico)": 4, "America - Santa_Isabel": 4, "Santa_Isabel": 4, "(UTC-07:00) Pacific Time (US & Canada)": 5, "Pacific Daylight Time": 5, "America - Dawson": 6, "Dawson": 6, "America - Los_Angeles": 6, "Los_Angeles": 6, "America - Tijuana": 6, "Tijuana": 6, "America - Vancouver": 6, "Vancouver": 6, "America - Whitehorse": 6, "Whitehorse": 6, "(UTC-08:00) Pacific Time (US & Canada)": 6, "PST": 6, "Pacific Standard Time": 6, "(UTC-07:00) Arizona": 7, "UMST": 7, "US Mountain Standard Time": 7, "America - Creston": 7, "Creston": 7, "America - Dawson_Creek": 7, "Dawson_Creek": 7, "America - Hermosillo": 7, "Hermosillo": 7, "America - Phoenix": 7, "Phoenix": 7, "Etc - GMT+7": 7, "GMT+7": 7, "(UTC-07:00) Chihuahua, La Paz, Mazatlan": 8, "MDT": 34, "Mountain Standard Time (Mexico)": 8, "America - Chihuahua": 8, "Chihuahua": 8, "America - Mazatlan": 8, "Mazatlan": 8, "(UTC-07:00) Mountain Time (US & Canada)": 9, "Mountain Standard Time": 9, "America - Boise": 9, "Boise": 9, "America - Cambridge_Bay": 9, "Cambridge_Bay": 9, "America - Denver": 9, "Denver": 9, "America - Edmonton": 9, "Edmonton": 9, "America - Inuvik": 9, "Inuvik": 9, "America - Ojinaga": 9, "Ojinaga": 9, "America - Yellowknife": 9, "Yellowknife": 9, "(UTC-06:00) Central America": 10, "CAST": 90, "Central America Standard Time": 10, "America - Belize": 10, "Belize": 10, "America - Costa_Rica": 10, "Costa_Rica": 10, "America - El_Salvador": 10, "El_Salvador": 10, "America - Guatemala": 10, "Guatemala": 10, "America - Managua": 10, "Managua": 10, "America - Tegucigalpa": 10, "Tegucigalpa": 10, "Etc - GMT+6": 10, "GMT+6": 10, "Pacific - Galapagos": 10, "Galapagos": 10, "(UTC-06:00) Central Time (US & Canada)": 11, "CDT": 12, "Central Standard Time": 11, "America - Chicago": 11, "Chicago": 11, "America - Indiana - Knox": 11, "Indiana": 16, "America - Indiana - Tell_City": 11, "America - Matamoros": 11, "Matamoros": 11, "America - Menominee": 11, "Menominee": 11, "America - North_Dakota - Beulah": 11, "North_Dakota": 11, "America - North_Dakota - Center": 11, "America - North_Dakota - New_Salem": 11, "America - Rainy_River": 11, "Rainy_River": 11, "America - Rankin_Inlet": 11, "Rankin_Inlet": 11, "America - Resolute": 11, "Resolute": 11, "America - Winnipeg": 11, "Winnipeg": 11, "(UTC-06:00) Guadalajara, Mexico City, Monterrey": 12, "Central Standard Time (Mexico)": 12, "America - Bahia_Banderas": 12, "Bahia_Banderas": 12, "America - Cancun": 12, "Cancun": 12, "America - Merida": 12, "Merida": 12, "America - Mexico_City": 12, "Mexico_City": 12, "America - Monterrey": 12, "Monterrey": 12, "(UTC-06:00) Saskatchewan": 13, "CCST": 13, "Canada Central Standard Time": 13, "America - Regina": 13, "Regina": 13, "America - Swift_Current": 13, "Swift_Current": 13, "(UTC-05:00) Bogota, Lima, Quito": 14, "SPST": 14, "SA Pacific Standard Time": 14, "America - Bogota": 14, "Bogota": 14, "America - Cayman": 14, "Cayman": 14, "America - Coral_Harbour": 14, "Coral_Harbour": 14, "America - Eirunepe": 14, "Eirunepe": 14, "America - Guayaquil": 14, "Guayaquil": 14, "America - Jamaica": 14, "Jamaica": 14, "America - Lima": 14, "Lima": 14, "America - Panama": 14, "Panama": 14, "America - Rio_Branco": 14, "Rio_Branco": 14, "Etc - GMT+5": 14, "GMT+5": 14, "(UTC-05:00) Eastern Time (US & Canada)": 15, "EDT": 15, "Eastern Standard Time": 15, "America - Detroit": 15, "Detroit": 15, "America - Havana": 15, "Havana": 15, "America - Indiana - Petersburg": 15, "America - Indiana - Vincennes": 15, "America - Indiana - Winamac": 15, "America - Iqaluit": 15, "Iqaluit": 15, "America - Kentucky - Monticello": 15, "Kentucky": 15, "America - Louisville": 15, "Louisville": 15, "America - Montreal": 15, "Montreal": 15, "America - Nassau": 15, "Nassau": 15, "America - New_York": 15, "New_York": 15, "America - Nipigon": 15, "Nipigon": 15, "America - Pangnirtung": 15, "Pangnirtung": 15, "America - Port-au-Prince": 15, "Port-au-Prince": 15, "America - Thunder_Bay": 15, "Thunder_Bay": 15, "America - Toronto": 15, "Toronto": 15, "(UTC-05:00) Indiana (East)": 16, "UEDT": 16, "US Eastern Standard Time": 16, "America - Indiana - Marengo": 16, "America - Indiana - Vevay": 16, "America - Indianapolis": 16, "Indianapolis": 16, "(UTC-04:30) Caracas": 17, "VST": 98, "Venezuela Standard Time": 17, "America - Caracas": 17, "Caracas": 17, "(UTC-04:00) Asuncion": 18, "PYT": 18, "Paraguay Standard Time": 18, "America - Asuncion": 18, "Asuncion": 18, "(UTC-04:00) Atlantic Time (Canada)": 19, "ADT": 65, "Atlantic Standard Time": 19, "America - Glace_Bay": 19, "Glace_Bay": 19, "America - Goose_Bay": 19, "Goose_Bay": 19, "America - Halifax": 19, "Halifax": 19, "America - Moncton": 19, "Moncton": 19, "America - Thule": 19, "Thule": 19, "Atlantic - Bermuda": 19, "Bermuda": 19, "(UTC-04:00) Cuiaba": 20, "CBST": 20, "Central Brazilian Standard Time": 20, "America - Campo_Grande": 20, "Campo_Grande": 20, "America - Cuiaba": 20, "Cuiaba": 20, "(UTC-04:00) Georgetown, La Paz, Manaus, San Juan": 21, "SWST": 21, "SA Western Standard Time": 21, "America - Anguilla": 21, "Anguilla": 21, "America - Antigua": 21, "Antigua": 21, "America - Aruba": 21, "Aruba": 21, "America - Barbados": 21, "Barbados": 21, "America - Blanc-Sablon": 21, "Blanc-Sablon": 21, "America - Boa_Vista": 21, "Boa_Vista": 21, "America - Curacao": 21, "Curacao": 21, "America - Dominica": 21, "Dominica": 21, "America - Grand_Turk": 21, "Grand_Turk": 21, "America - Grenada": 21, "Grenada": 21, "America - Guadeloupe": 21, "Guadeloupe": 21, "America - Guyana": 21, "Guyana": 21, "America - Kralendijk": 21, "Kralendijk": 21, "America - La_Paz": 21, "La_Paz": 21, "America - Lower_Princes": 21, "Lower_Princes": 21, "America - Manaus": 21, "Manaus": 21, "America - Marigot": 21, "Marigot": 21, "America - Martinique": 21, "Martinique": 21, "America - Montserrat": 21, "Montserrat": 21, "America - Port_of_Spain": 21, "Port_of_Spain": 21, "America - Porto_Velho": 21, "Porto_Velho": 21, "America - Puerto_Rico": 21, "Puerto_Rico": 21, "America - Santo_Domingo": 21, "Santo_Domingo": 21, "America - St_Barthelemy": 21, "St_Barthelemy": 21, "America - St_Kitts": 21, "St_Kitts": 21, "America - St_Lucia": 21, "St_Lucia": 21, "America - St_Thomas": 21, "St_Thomas": 21, "America - St_Vincent": 21, "St_Vincent": 21, "America - Tortola": 21, "Tortola": 21, "Etc - GMT+4": 21, "GMT+4": 21, "(UTC-04:00) Santiago": 22, "PSST": 22, "Pacific SA Standard Time": 22, "America - Santiago": 22, "Santiago": 22, "Antarctica - Palmer": 22, "Palmer": 22, "(UTC-03:30) Newfoundland": 23, "NDT": 23, "Newfoundland Standard Time": 23, "America - St_Johns": 23, "St_Johns": 23, "(UTC-03:00) Brasilia": 24, "ESAST": 24, "E. South America Standard Time": 24, "America - Sao_Paulo": 24, "Sao_Paulo": 24, "(UTC-03:00) Buenos Aires": 25, "AST": 69, "Argentina Standard Time": 25, "America - Argentina - La_Rioja": 25, "Argentina": 25, "America - Argentina - Rio_Gallegos": 25, "America - Argentina - Salta": 25, "America - Argentina - San_Juan": 25, "America - Argentina - San_Luis": 25, "America - Argentina - Tucuman": 25, "America - Argentina - Ushuaia": 25, "America - Buenos_Aires": 25, "Buenos_Aires": 25, "America - Catamarca": 25, "Catamarca": 25, "America - Cordoba": 25, "Cordoba": 25, "America - Jujuy": 25, "Jujuy": 25, "America - Mendoza": 25, "Mendoza": 25, "(UTC-03:00) Cayenne, Fortaleza": 26, "SEST": 26, "SA Eastern Standard Time": 26, "America - Araguaina": 26, "Araguaina": 26, "America - Belem": 26, "Belem": 26, "America - Cayenne": 26, "Cayenne": 26, "America - Fortaleza": 26, "Fortaleza": 26, "America - Maceio": 26, "Maceio": 26, "America - Paramaribo": 26, "Paramaribo": 26, "America - Recife": 26, "Recife": 26, "America - Santarem": 26, "Santarem": 26, "Antarctica - Rothera": 26, "Rothera": 26, "Atlantic - Stanley": 26, "Stanley": 26, "Etc - GMT+3": 26, "GMT+3": 26, "(UTC-03:00) Greenland": 27, "GDT": 46, "Greenland Standard Time": 27, "America - Godthab": 27, "Godthab": 27, "(UTC-03:00) Montevideo": 28, "MST": 102, "Montevideo Standard Time": 28, "America - Montevideo": 28, "Montevideo": 28, "(UTC-03:00) Salvador": 29, "BST": 77, "Bahia Standard Time": 29, "America - Bahia": 29, "Bahia": 29, "(UTC-02:00) Coordinated Universal Time-02": 30, "UTC-02": 30, "America - Noronha": 30, "Noronha": 30, "Atlantic - South_Georgia": 30, "South_Georgia": 30, "Etc - GMT+2": 30, "GMT+2": 30, "(UTC-02:00) Mid-Atlantic - Old": 31, "Mid-Atlantic Standard Time": 31, "(UTC-01:00) Azores": 32, "Azores Standard Time": 32, "America - Scoresbysund": 32, "Scoresbysund": 32, "Atlantic - Azores": 32, "Azores": 32, "(UTC-01:00) Cape Verde Is.": 33, "CVST": 33, "Cape Verde Standard Time": 33, "Atlantic - Cape_Verde": 33, "Cape_Verde": 33, "Etc - GMT+1": 33, "GMT+1": 33, "(UTC) Casablanca": 34, "Morocco Standard Time": 34, "Africa - Casablanca": 34, "Casablanca": 34, "Africa - El_Aaiun": 34, "El_Aaiun": 34, "(UTC) Coordinated Universal Time": 35, "UTC": 35, "America - Danmarkshavn": 35, "Danmarkshavn": 35, "Etc - GMT": 35, "GMT": 36, "(UTC) Edinburgh, London": 36, "GMT Standard Time": 38, "Europe - Isle_of_Man": 37, "Isle_of_Man": 37, "Europe - Guernsey": 37, "Guernsey": 37, "Europe - Jersey": 37, "Jersey": 37, "Europe - London": 37, "London": 37, "(UTC+01:00) Edinburgh, London": 37, "British Summer Time": 37, "(UTC) Dublin, Lisbon": 38, "Atlantic - Canary": 38, "Canary": 38, "Atlantic - Faeroe": 38, "Faeroe": 38, "Atlantic - Madeira": 38, "Madeira": 38, "Europe - Dublin": 38, "Dublin": 38, "Europe - Lisbon": 38, "Lisbon": 38, "(UTC) Monrovia, Reykjavik": 39, "GST": 39, "Greenwich Standard Time": 39, "Africa - Abidjan": 39, "Abidjan": 39, "Africa - Accra": 39, "Accra": 39, "Africa - Bamako": 39, "Bamako": 39, "Africa - Banjul": 39, "Banjul": 39, "Africa - Bissau": 39, "Bissau": 39, "Africa - Conakry": 39, "Conakry": 39, "Africa - Dakar": 39, "Dakar": 39, "Africa - Freetown": 39, "Freetown": 39, "Africa - Lome": 39, "Lome": 39, "Africa - Monrovia": 39, "Monrovia": 39, "Africa - Nouakchott": 39, "Nouakchott": 39, "Africa - Ouagadougou": 39, "Ouagadougou": 39, "Africa - Sao_Tome": 39, "Sao_Tome": 39, "Atlantic - Reykjavik": 39, "Reykjavik": 39, "Atlantic - St_Helena": 39, "St_Helena": 39, "(UTC+01:00) Amsterdam, Berlin, Bern, Rome, Stockholm, Vienna": 40, "WEDT": 40, "W. Europe Standard Time": 40, "Arctic - Longyearbyen": 40, "Longyearbyen": 40, "Europe - Amsterdam": 40, "Amsterdam": 40, "Europe - Andorra": 40, "Andorra": 40, "Europe - Berlin": 40, "Berlin": 40, "Europe - Busingen": 40, "Busingen": 40, "Europe - Gibraltar": 40, "Gibraltar": 40, "Europe - Luxembourg": 40, "Luxembourg": 40, "Europe - Malta": 40, "Malta": 40, "Europe - Monaco": 40, "Monaco": 40, "Europe - Oslo": 40, "Oslo": 40, "Europe - Rome": 40, "Rome": 40, "Europe - San_Marino": 40, "San_Marino": 40, "Europe - Stockholm": 40, "Stockholm": 40, "Europe - Vaduz": 40, "Vaduz": 40, "Europe - Vatican": 40, "Vatican": 40, "Europe - Vienna": 40, "Vienna": 40, "Europe - Zurich": 40, "Zurich": 40, "(UTC+01:00) Belgrade, Bratislava, Budapest, Ljubljana, Prague": 41, "CEDT": 43, "Central Europe Standard Time": 41, "Europe - Belgrade": 41, "Belgrade": 41, "Europe - Bratislava": 41, "Bratislava": 41, "Europe - Budapest": 41, "Budapest": 41, "Europe - Ljubljana": 41, "Ljubljana": 41, "Europe - Podgorica": 41, "Podgorica": 41, "Europe - Prague": 41, "Prague": 41, "Europe - Tirane": 41, "Tirane": 41, "(UTC+01:00) Brussels, Copenhagen, Madrid, Paris": 42, "RDT": 42, "Romance Standard Time": 42, "Africa - Ceuta": 42, "Ceuta": 42, "Europe - Brussels": 42, "Brussels": 42, "Europe - Copenhagen": 42, "Copenhagen": 42, "Europe - Madrid": 42, "Madrid": 42, "Europe - Paris": 42, "Paris": 42, "(UTC+01:00) Sarajevo, Skopje, Warsaw, Zagreb": 43, "Central European Standard Time": 43, "Europe - Sarajevo": 43, "Sarajevo": 43, "Europe - Skopje": 43, "Skopje": 43, "Europe - Warsaw": 43, "Warsaw": 43, "Europe - Zagreb": 43, "Zagreb": 43, "(UTC+01:00) West Central Africa": 44, "WCAST": 44, "W. Central Africa Standard Time": 44, "Africa - Algiers": 44, "Algiers": 44, "Africa - Bangui": 44, "Bangui": 44, "Africa - Brazzaville": 44, "Brazzaville": 44, "Africa - Douala": 44, "Douala": 44, "Africa - Kinshasa": 44, "Kinshasa": 44, "Africa - Lagos": 44, "Lagos": 44, "Africa - Libreville": 44, "Libreville": 44, "Africa - Luanda": 44, "Luanda": 44, "Africa - Malabo": 44, "Malabo": 44, "Africa - Ndjamena": 44, "Ndjamena": 44, "Africa - Niamey": 44, "Niamey": 44, "Africa - Porto-Novo": 44, "Porto-Novo": 44, "Africa - Tunis": 44, "Tunis": 44, "Etc - GMT-1": 44, "GMT-1": 44, "(UTC+01:00) Windhoek": 45, "NST": 75, "Namibia Standard Time": 45, "Africa - Windhoek": 45, "Windhoek": 45, "(UTC+02:00) Athens, Bucharest": 46, "GTB Standard Time": 46, "Asia - Nicosia": 50, "Nicosia": 50, "Europe - Athens": 50, "Athens": 50, "Europe - Bucharest": 50, "Bucharest": 50, "Europe - Chisinau": 50, "Chisinau": 50, "(UTC+02:00) Beirut": 47, "MEDT": 47, "Middle East Standard Time": 47, "Asia - Beirut": 47, "Beirut": 47, "(UTC+02:00) Cairo": 48, "EST": 48, "Egypt Standard Time": 48, "Africa - Cairo": 48, "Cairo": 48, "(UTC+02:00) Damascus": 49, "SDT": 49, "Syria Standard Time": 49, "Asia - Damascus": 49, "Damascus": 49, "(UTC+02:00) E. Europe": 50, "EEDT": 50, "E. Europe Standard Time": 50, "Europe - Helsinki": 52, "Helsinki": 52, "Europe - Kiev": 52, "Kiev": 52, "Europe - Mariehamn": 52, "Mariehamn": 52, "Europe - Nicosia": 50, "Europe - Riga": 52, "Riga": 52, "Europe - Sofia": 52, "Sofia": 52, "Europe - Tallinn": 52, "Tallinn": 52, "Europe - Uzhgorod": 52, "Uzhgorod": 52, "Europe - Vilnius": 52, "Vilnius": 52, "Europe - Zaporozhye": 52, "Zaporozhye": 52, "(UTC+02:00) Harare, Pretoria": 51, "SAST": 79, "South Africa Standard Time": 51, "Africa - Blantyre": 51, "Blantyre": 51, "Africa - Bujumbura": 51, "Bujumbura": 51, "Africa - Gaborone": 51, "Gaborone": 51, "Africa - Harare": 51, "Harare": 51, "Africa - Johannesburg": 51, "Johannesburg": 51, "Africa - Kigali": 51, "Kigali": 51, "Africa - Lubumbashi": 51, "Lubumbashi": 51, "Africa - Lusaka": 51, "Lusaka": 51, "Africa - Maputo": 51, "Maputo": 51, "Africa - Maseru": 51, "Maseru": 51, "Africa - Mbabane": 51, "Mbabane": 51, "Etc - GMT-2": 51, "GMT-2": 51, "(UTC+02:00) Helsinki, Kyiv, Riga, Sofia, Tallinn, Vilnius": 52, "FDT": 52, "FLE Standard Time": 52, "(UTC+03:00) Istanbul": 53, "TDT": 53, "Turkey Standard Time": 53, "Europe - Istanbul": 53, "Istanbul": 53, "(UTC+02:00) Jerusalem": 54, "JDT": 54, "Israel Standard Time": 54, "Asia - Jerusalem": 54, "Jerusalem": 54, "(UTC+02:00) Tripoli": 55, "LST": 55, "Libya Standard Time": 55, "Africa - Tripoli": 55, "Tripoli": 55, "(UTC+03:00) Amman": 56, "JST": 88, "Jordan Standard Time": 56, "Asia - Amman": 56, "Amman": 56, "(UTC+03:00) Baghdad": 57, "Arabic Standard Time": 57, "Asia - Baghdad": 57, "Baghdad": 57, "(UTC+02:00) Kaliningrad": 58, "KST": 89, "Kaliningrad Standard Time": 58, "Europe - Kaliningrad": 58, "Kaliningrad": 58, "(UTC+03:00) Kuwait, Riyadh": 59, "Arab Standard Time": 59, "Asia - Aden": 59, "Aden": 59, "Asia - Bahrain": 59, "Bahrain": 59, "Asia - Kuwait": 59, "Kuwait": 59, "Asia - Qatar": 59, "Qatar": 59, "Asia - Riyadh": 59, "Riyadh": 59, "(UTC+03:00) Nairobi": 60, "EAST": 92, "E. Africa Standard Time": 60, "Africa - Addis_Ababa": 60, "Addis_Ababa": 60, "Africa - Asmera": 60, "Asmera": 60, "Africa - Dar_es_Salaam": 60, "Dar_es_Salaam": 60, "Africa - Djibouti": 60, "Djibouti": 60, "Africa - Juba": 60, "Juba": 60, "Africa - Kampala": 60, "Kampala": 60, "Africa - Khartoum": 60, "Khartoum": 60, "Africa - Mogadishu": 60, "Mogadishu": 60, "Africa - Nairobi": 60, "Nairobi": 60, "Antarctica - Syowa": 60, "Syowa": 60, "Etc - GMT-3": 60, "GMT-3": 60, "Indian - Antananarivo": 60, "Antananarivo": 60, "Indian - Comoro": 60, "Comoro": 60, "Indian - Mayotte": 60, "Mayotte": 60, "(UTC+03:00) Moscow, St. Petersburg, Volgograd, Minsk": 61, "MSK": 61, "Moscow Standard Time": 61, "Europe - Kirov": 61, "Kirov": 61, "Europe - Moscow": 61, "Moscow": 61, "Europe - Simferopol": 61, "Simferopol": 61, "Europe - Volgograd": 61, "Volgograd": 61, "Europe - Minsk": 61, "Minsk": 61, "(UTC+04:00) Samara, Ulyanovsk, Saratov": 62, "SAMT": 62, "Samara Time": 62, "Europe - Astrakhan": 62, "Astrakhan": 62, "Europe - Samara": 62, "Samara": 62, "Europe - Ulyanovsk": 62, "Ulyanovsk": 62, "(UTC+03:30) Tehran": 63, "IDT": 63, "Iran Standard Time": 63, "Asia - Tehran": 63, "Tehran": 63, "(UTC+04:00) Abu Dhabi, Muscat": 64, "Arabian Standard Time": 64, "Asia - Dubai": 64, "Dubai": 64, "Asia - Muscat": 64, "Muscat": 64, "Etc - GMT-4": 64, "GMT-4": 64, "(UTC+04:00) Baku": 65, "Azerbaijan Standard Time": 65, "Asia - Baku": 65, "Baku": 65, "(UTC+04:00) Port Louis": 66, "Mauritius Standard Time": 66, "Indian - Mahe": 66, "Mahe": 66, "Indian - Mauritius": 66, "Mauritius": 66, "Indian - Reunion": 66, "Reunion": 66, "(UTC+04:00) Tbilisi": 67, "GET": 67, "Georgian Standard Time": 67, "Asia - Tbilisi": 67, "Tbilisi": 67, "(UTC+04:00) Yerevan": 68, "CST": 81, "Caucasus Standard Time": 68, "Asia - Yerevan": 68, "Yerevan": 68, "(UTC+04:30) Kabul": 69, "Afghanistan Standard Time": 69, "Asia - Kabul": 69, "Kabul": 69, "(UTC+05:00) Ashgabat, Tashkent": 70, "WAST": 84, "West Asia Standard Time": 70, "Antarctica - Mawson": 70, "Mawson": 70, "Asia - Aqtau": 70, "Aqtau": 70, "Asia - Aqtobe": 70, "Aqtobe": 70, "Asia - Ashgabat": 70, "Ashgabat": 70, "Asia - Dushanbe": 70, "Dushanbe": 70, "Asia - Oral": 70, "Oral": 70, "Asia - Samarkand": 70, "Samarkand": 70, "Asia - Tashkent": 70, "Tashkent": 70, "Etc - GMT-5": 70, "GMT-5": 70, "Indian - Kerguelen": 70, "Kerguelen": 70, "Indian - Maldives": 70, "Maldives": 70, "(UTC+05:00) Yekaterinburg": 71, "YEKT": 71, "Yekaterinburg Time": 71, "Asia - Yekaterinburg": 71, "Yekaterinburg": 71, "(UTC+05:00) Islamabad, Karachi": 72, "PKT": 72, "Pakistan Standard Time": 72, "Asia - Karachi": 72, "Karachi": 72, "(UTC+05:30) Chennai, Kolkata, Mumbai, New Delhi": 73, "IST": 73, "India Standard Time": 73, "Asia - Kolkata": 73, "Kolkata": 73, "(UTC+05:30) Sri Jayawardenepura": 74, "SLST": 74, "Sri Lanka Standard Time": 74, "Asia - Colombo": 74, "Colombo": 74, "(UTC+05:45) Kathmandu": 75, "Nepal Standard Time": 75, "Asia - Kathmandu": 75, "Kathmandu": 75, "(UTC+06:00) Nur-Sultan (Astana)": 76, "Central Asia Standard Time": 76, "Antarctica - Vostok": 76, "Vostok": 76, "Asia - Almaty": 76, "Almaty": 76, "Asia - Bishkek": 76, "Bishkek": 76, "Asia - Qyzylorda": 76, "Qyzylorda": 76, "Asia - Urumqi": 76, "Urumqi": 76, "Etc - GMT-6": 76, "GMT-6": 76, "Indian - Chagos": 76, "Chagos": 76, "(UTC+06:00) Dhaka": 77, "Bangladesh Standard Time": 77, "Asia - Dhaka": 77, "Dhaka": 77, "Asia - Thimphu": 77, "Thimphu": 77, "(UTC+06:30) Yangon (Rangoon)": 78, "Myanmar Standard Time": 78, "Asia - Rangoon": 78, "Rangoon": 78, "Indian - Cocos": 78, "Cocos": 78, "(UTC+07:00) Bangkok, Hanoi, Jakarta": 79, "SE Asia Standard Time": 79, "Antarctica - Davis": 79, "Davis": 79, "Asia - Bangkok": 79, "Bangkok": 79, "Asia - Hovd": 79, "Hovd": 79, "Asia - Jakarta": 79, "Jakarta": 79, "Asia - Phnom_Penh": 79, "Phnom_Penh": 79, "Asia - Pontianak": 79, "Pontianak": 79, "Asia - Saigon": 79, "Saigon": 79, "Asia - Vientiane": 79, "Vientiane": 79, "Etc - GMT-7": 79, "GMT-7": 79, "Indian - Christmas": 79, "Christmas": 79, "(UTC+07:00) Novosibirsk": 80, "NCAST": 80, "N. Central Asia Standard Time": 80, "Asia - Novokuznetsk": 80, "Novokuznetsk": 80, "Asia - Novosibirsk": 80, "Novosibirsk": 80, "Asia - Omsk": 80, "Omsk": 80, "(UTC+08:00) Beijing, Chongqing, Hong Kong, Urumqi": 81, "China Standard Time": 81, "Asia - Hong_Kong": 81, "Hong_Kong": 81, "Asia - Macau": 81, "Macau": 81, "Asia - Shanghai": 81, "Shanghai": 81, "(UTC+08:00) Krasnoyarsk": 82, "NAST": 82, "North Asia Standard Time": 82, "Asia - Krasnoyarsk": 82, "Krasnoyarsk": 82, "(UTC+08:00) Kuala Lumpur, Singapore": 83, "MPST": 83, "Singapore Standard Time": 83, "Asia - Brunei": 83, "Brunei": 83, "Asia - Kuala_Lumpur": 83, "Kuala_Lumpur": 83, "Asia - Kuching": 83, "Kuching": 83, "Asia - Makassar": 83, "Makassar": 83, "Asia - Manila": 83, "Manila": 83, "Asia - Singapore": 83, "Singapore": 83, "Etc - GMT-8": 83, "GMT-8": 83, "(UTC+08:00) Perth": 84, "W. Australia Standard Time": 84, "Antarctica - Casey": 84, "Casey": 84, "Australia - Perth": 84, "Perth": 84, "(UTC+08:00) Taipei": 85, "TST": 104, "Taipei Standard Time": 85, "Asia - Taipei": 85, "Taipei": 85, "(UTC+08:00) Ulaanbaatar": 86, "UST": 86, "Ulaanbaatar Standard Time": 86, "Asia - Choibalsan": 86, "Choibalsan": 86, "Asia - Ulaanbaatar": 86, "Ulaanbaatar": 86, "(UTC+08:00) Irkutsk": 87, "NAEST": 87, "North Asia East Standard Time": 87, "Asia - Irkutsk": 87, "Irkutsk": 87, "(UTC+09:00) Osaka, Sapporo, Tokyo": 88, "Japan Standard Time": 88, "Asia - Dili": 88, "Dili": 88, "Asia - Jayapura": 88, "Jayapura": 88, "Asia - Tokyo": 88, "Tokyo": 88, "Etc - GMT-9": 88, "GMT-9": 88, "Pacific - Palau": 88, "Palau": 88, "(UTC+09:00) Seoul": 89, "Korea Standard Time": 89, "Asia - Pyongyang": 89, "Pyongyang": 89, "Asia - Seoul": 89, "Seoul": 89, "(UTC+09:30) Adelaide": 90, "Cen. Australia Standard Time": 90, "Australia - Adelaide": 90, "Adelaide": 90, "Australia - Broken_Hill": 90, "Broken_Hill": 90, "(UTC+09:30) Darwin": 91, "ACST": 91, "AUS Central Standard Time": 91, "Australia - Darwin": 91, "Darwin": 91, "(UTC+10:00) Brisbane": 92, "E. Australia Standard Time": 92, "Australia - Brisbane": 92, "Brisbane": 92, "Australia - Lindeman": 92, "Lindeman": 92, "(UTC+10:00) Canberra, Melbourne, Sydney": 93, "AEST": 93, "AUS Eastern Standard Time": 93, "Australia - Melbourne": 93, "Melbourne": 93, "Australia - Sydney": 93, "Sydney": 93, "(UTC+10:00) Guam, Port Moresby": 94, "WPST": 94, "West Pacific Standard Time": 94, "Antarctica - DumontDUrville": 94, "DumontDUrville": 94, "Etc - GMT-10": 94, "GMT-10": 94, "Pacific - Guam": 94, "Guam": 94, "Pacific - Port_Moresby": 94, "Port_Moresby": 94, "Pacific - Saipan": 94, "Saipan": 94, "Pacific - Truk": 94, "Truk": 94, "(UTC+10:00) Hobart": 95, "Tasmania Standard Time": 95, "Australia - Currie": 95, "Currie": 95, "Australia - Hobart": 95, "Hobart": 95, "(UTC+09:00) Yakutsk": 96, "YST": 96, "Yakutsk Standard Time": 96, "Asia - Chita": 96, "Chita": 96, "Asia - Khandyga": 96, "Khandyga": 96, "Asia - Yakutsk": 96, "Yakutsk": 96, "(UTC+11:00) Solomon Is., New Caledonia": 97, "CPST": 97, "Central Pacific Standard Time": 97, "Antarctica - Macquarie": 97, "Macquarie": 97, "Etc - GMT-11": 97, "GMT-11": 97, "Pacific - Efate": 97, "Efate": 97, "Pacific - Guadalcanal": 97, "Guadalcanal": 97, "Pacific - Kosrae": 97, "Kosrae": 97, "Pacific - Noumea": 97, "Noumea": 97, "Pacific - Ponape": 97, "Ponape": 97, "(UTC+11:00) Vladivostok": 98, "Vladivostok Standard Time": 98, "Asia - Sakhalin": 98, "Sakhalin": 98, "Asia - Ust-Nera": 98, "Ust-Nera": 98, "Asia - Vladivostok": 98, "Vladivostok": 98, "(UTC+12:00) Auckland, Wellington": 99, "NZST": 99, "New Zealand Standard Time": 99, "Antarctica - McMurdo": 99, "McMurdo": 99, "Pacific - Auckland": 99, "Auckland": 99, "(UTC+12:00) Coordinated Universal Time+12": 100, "UTC+12": 100, "Etc - GMT-12": 100, "GMT-12": 100, "Pacific - Funafuti": 100, "Funafuti": 100, "Pacific - Kwajalein": 100, "Kwajalein": 100, "Pacific - Majuro": 100, "Majuro": 100, "Pacific - Nauru": 100, "Nauru": 100, "Pacific - Tarawa": 100, "Tarawa": 100, "Pacific - Wake": 100, "Wake": 100, "Pacific - Wallis": 100, "Wallis": 100, "(UTC+12:00) Fiji": 101, "FST": 101, "Fiji Standard Time": 101, "Pacific - Fiji": 101, "Fiji": 101, "(UTC+12:00) Magadan": 102, "Magadan Standard Time": 102, "Asia - Anadyr": 102, "Anadyr": 102, "Asia - Kamchatka": 103, "Kamchatka": 103, "Asia - Magadan": 102, "Magadan": 102, "Asia - Srednekolymsk": 102, "Srednekolymsk": 102, "(UTC+12:00) Petropavlovsk-Kamchatsky - Old": 103, "KDT": 103, "Kamchatka Standard Time": 103, "(UTC+13:00) Nuku'alofa": 104, "Tonga Standard Time": 104, "Etc - GMT-13": 104, "GMT-13": 104, "Pacific - Enderbury": 104, "Enderbury": 104, "Pacific - Fakaofo": 104, "Fakaofo": 104, "Pacific - Tongatapu": 104, "Tongatapu": 104, "(UTC+13:00) Samoa": 105, "SST": 105, "Samoa Standard Time": 105, "Pacific - Apia": 105, "Apia": 105}}
